webullpaysdkmdata/__init__.py
webullpaysdkmdata/common/__init__.py
webullpaysdkmdata/common/category.py
webullpaysdkmdata/common/direction.py
webullpaysdkmdata/common/expiration_cycle.py
webullpaysdkmdata/common/instrument_status.py
webullpaysdkmdata/common/subscribe_type.py
webullpaysdkmdata/common/timespan.py
webullpaysdkmdata/quotes/__init__.py
webullpaysdkmdata/quotes/instrument.py
webullpaysdkmdata/quotes/market_data.py
webullpaysdkmdata/request/__init__.py
webullpaysdkmdata/request/get_historical_bars_request.py
webullpaysdkmdata/request/get_instruments_request.py
webullpaysdkmdata/request/get_quotes_request.py
webullpaysdkmdata/request/get_snapshot_request.py
webullpay_python_sdk_mdata-0.1.0.dist-info/METADATA
webullpay_python_sdk_mdata-0.1.0.dist-info/WHEEL
webullpay_python_sdk_mdata-0.1.0.dist-info/top_level.txt
webullpay_python_sdk_mdata-0.1.0.dist-info/RECORD
